fsspec_utils/__init__.py
fsspec_utils/core/__init__.py
fsspec_utils/core/base.py
fsspec_utils/core/ext.py
fsspec_utils/storage_options/__init__.py
fsspec_utils/storage_options/base.py
fsspec_utils/storage_options/cloud.py
fsspec_utils/storage_options/core.py
fsspec_utils/storage_options/git.py
fsspec_utils/utils/__init__.py
fsspec_utils/utils/datetime.py
fsspec_utils/utils/logging.py
fsspec_utils/utils/misc.py
fsspec_utils/utils/polars.py
fsspec_utils/utils/pyarrow.py
fsspec_utils/utils/sql.py
fsspec_utils/utils/types.py
fsspec_utils-0.2.6.7.dist-info/METADATA
fsspec_utils-0.2.6.7.dist-info/WHEEL
fsspec_utils-0.2.6.7.dist-info/licenses/LICENSE
fsspec_utils-0.2.6.7.dist-info/RECORD
