Metadata-Version: 2.4
Name: fsspec-utils
Version: 0.2.6.7
Summary: Enhanced utilities and extensions for fsspec filesystems with multi-format I/O support
Project-URL: Homepage, https://github.com/legout/fsspec-utils
Project-URL: Documentation, https://legout.github.io/fsspec-utils
Project-URL: Repository, https://github.com/legout/fsspec-utils.git
Project-URL: Issues, https://github.com/legout/fsspec-utils/issues
Author-email: legout <ligno.blades@gmail.com>
License-Expression: MIT
License-File: LICENSE
Keywords: azure,cloud-storage,csv,data-io,filesystem,fsspec,gcs,json,parquet,s3
Classifier: Development Status :: 4 - Beta
Classifier: Intended Audience :: Developers
Classifier: License :: OSI Approved :: MIT License
Classifier: Operating System :: OS Independent
Classifier: Programming Language :: Python :: 3
Classifier: Programming Language :: Python :: 3.11
Classifier: Programming Language :: Python :: 3.12
Classifier: Topic :: Scientific/Engineering :: Information Analysis
Classifier: Topic :: Software Development :: Libraries :: Python Modules
Classifier: Topic :: System :: Filesystems
Requires-Python: >=3.11
Requires-Dist: fsspec>=2025.1.0
Requires-Dist: joblib>=1.5.0
Requires-Dist: loguru>=0.7.0
Requires-Dist: msgspec>=0.18.0
Requires-Dist: orjson>=3.11.0
Requires-Dist: pandas>=2.2.0
Requires-Dist: polars>=1.30.0
Requires-Dist: pyarrow>=20.0.0
Requires-Dist: pyyaml>=6.0
Requires-Dist: requests>=2.25.0
Requires-Dist: rich>=14.0.0
Requires-Dist: sqlglot>=27.16.3
Provides-Extra: aws
Requires-Dist: boto3>=1.26.0; extra == 'aws'
Requires-Dist: s3fs>=2025.1.0; extra == 'aws'
Provides-Extra: azure
Requires-Dist: adlfs>=2024.12.0; extra == 'azure'
Provides-Extra: dev
Requires-Dist: mkdocs; extra == 'dev'
Requires-Dist: mkdocstrings[python]>=0.30.0; extra == 'dev'
Requires-Dist: mypy>=1.0.0; extra == 'dev'
Requires-Dist: pre-commit>=3.0.0; extra == 'dev'
Requires-Dist: pytest-cov>=4.0.0; extra == 'dev'
Requires-Dist: pytest-mock>=3.10.0; extra == 'dev'
Requires-Dist: pytest>=7.0.0; extra == 'dev'
Requires-Dist: ruff>=0.1.0; extra == 'dev'
Provides-Extra: gcp
Requires-Dist: gcsfs>=2025.1.0; extra == 'gcp'
